locus_rs-0.2.2.dist-info/METADATA
locus_rs-0.2.2.dist-info/WHEEL
locus_rs/__init__.py
locus_rs/locus_rs.cpython-312-aarch64-linux-gnu.so
locus_rs-0.2.2.dist-info/RECORD
