Metadata-Version: 2.3
Name: locus_rs
Version: 0.2.2
